webinfo
