Metadata-Version: 1.0
Name: webinfo
Version: 0.1.1
Summary: Get some info about a domain.
Home-page: http://github.com/pascalmouret/webinfo
Author: Pascal Mouret
Author-email: pascal.mouret@me.com
License: BSD
Platform: OS Independent
Classifier: Development Status :: 4 - Beta
Classifier: Intended Audience :: Developers
Classifier: License :: OSI Approved :: BSD License
Classifier: Operating System :: OS Independent
Classifier: Programming Language :: Python
Classifier: Topic :: Internet :: WWW/HTTP
